osp_marketing_tools/__init__.py
osp_marketing_tools/codes-llm.md
osp_marketing_tools/guide-llm.md
osp_marketing_tools/meta-llm.md
osp_marketing_tools/on-page-seo-guide.md
osp_marketing_tools/product-value-map-llm.md
osp_marketing_tools/server.py
iflow_mcp_osp_marketing_tools-0.1.0.dist-info/METADATA
iflow_mcp_osp_marketing_tools-0.1.0.dist-info/WHEEL
iflow_mcp_osp_marketing_tools-0.1.0.dist-info/entry_points.txt
iflow_mcp_osp_marketing_tools-0.1.0.dist-info/RECORD
