Metadata-Version: 2.4
Name: iflow-mcp_osp-marketing-tools
Version: 0.1.0
Summary: OSP Marketing Tools using Model Context Protocol
Author: Robert Douglass, Tracy Evans, Jeffrey McGuire, other Open Srategy Partners contributors
Requires-Python: <3.14,>=3.10
Requires-Dist: aiohttp==3.11.11
Requires-Dist: mcp[cli]
